playdionsteam_py-2025.5.13.dist-info/licenses/LICENSE
steampy/IPlayerService.py
steampy/ISteamNews.py
steampy/ISteamUser.py
steampy/ISteamUserStats.py
steampy/__init__.py
playdionsteam_py-2025.5.13.dist-info/METADATA
playdionsteam_py-2025.5.13.dist-info/WHEEL
playdionsteam_py-2025.5.13.dist-info/top_level.txt
playdionsteam_py-2025.5.13.dist-info/RECORD
